bingcnsearch/__init__.py
bingcnsearch/user_agents.py
bingcnsearch_python-1.0.2.dist-info/METADATA
bingcnsearch_python-1.0.2.dist-info/WHEEL
bingcnsearch_python-1.0.2.dist-info/licenses/LICENSE
bingcnsearch_python-1.0.2.dist-info/RECORD
