Metadata-Version: 2.4
Name: bingcnsearch-python
Version: 1.0.2
Summary: A Python library for scraping the cn.bing.com search engine.
Project-URL: Homepage, https://github.com/tianxuan911/bingcnsearch
Project-URL: Issues, https://github.com/tianxuan911/bingcnsearch/issues
Author-email: Tian <tianxuan911@aliyun.com>
License: MIT License
License-File: LICENSE
Classifier: Operating System :: OS Independent
Classifier: Programming Language :: Python :: 3
Requires-Python: >=3.6
Requires-Dist: beautifulsoup4>=4.9
Requires-Dist: requests>=2.20
